generated/FullAdderModule.v
module FullAdderModule(
  input   clock,
  input   reset,
  input   io_a,
  input   io_b,
  input   io_cin,
  output  io_sum,
  output  io_cout
);
  assign io_sum = io_a ^ io_b ^ io_cin; // @[FullAdder.scala 17:25]
  assign io_cout = io_a & io_b | io_b & io_cin | io_a & io_cin; // @[FullAdder.scala 19:46]
endmodule

test_run_dir/FullAdder_should_work/FullAdderModule.vcd
$date
2023-12-23T17:15+0000
$end
$version
0.2
$end
$comment

$end
$timescale 1ns  $end
$scope module FullAdderModule $end
 $var wire 1 ! io_b $end
 $var wire 1 " io_cin $end
 $var wire 1 # clock $end
 $var wire 1 $ io_cout $end
 $var wire 1 % io_a $end
 $var wire 1 & reset $end
 $var wire 1 ' io_sum $end
$upscope $end
$enddefinitions $end
$dumpvars
0%
0"
0&
0#
0'
0$
0!
$end
#0
1&
#1
1#
#6
0&
0#
#11
1#
#16
1"
0#
1'
#21
1#
#26
1!
0"
0#
1'
0$
#31
1#
#36
1"
0#
0'
1$
#41
1#
#46
0!
1%
0"
0#
1'
0$
#51
1#
#56
1"
0#
0'
1$
#61
1#
#66
1!
0"
0#
0'
#71
1#
#76
1"
0#
1'
#81
1#
#86
0!
0%
0"
0#
